{
  "plugins": [
    {
      "id": "SF-884",
      "category": "Device",
      "name": "SF-884 scales",
      "type": "scales",
      "version": "0.1",
      "descriptionLocation": "config/devices/SF-884/description-0.1.txt",
      "infLocation": "config/devices/SF-884/SF-884-INF-0.1.json"
    },
    {
      "id": "AustraliaPost",
      "category": "URL",
      "name": "Australia Post",
      "version": "0.1",
      "descriptionLocation": "scripts/Australia Post/description-0.1.txt",
      "infLocation": "scripts/Australia Post/AustraliaPost-INF-0.1.json"
    },
    {
      "id": "EbayReceiver",
      "category": "LocalScript",
      "name": "Receiver details from ebay",
      "version": "0.1",
      "descriptionLocation": "scripts/ebay/ebayReceiver/description-0.1.txt",
      "infLocation": "scripts/ebay/ebayReceiver/ebayReceiver-INF-0.1.json"
    }     
  ]
}
